[
  {
    "candidate_id": "C001",
    "question_id": "Q1",
    "analysis": {
      "reasoning": {
        "score": 30,
        "matched_keywords": [
          "reason",
          "explain"
        ]
      },
      "scenario": {
        "score": 0,
        "matched_keywords": []
      },
      "clarity": {
        "score": 100,
        "word_count": 30
      },
      "structure": {
        "score": 12,
        "structure_detected": [
          "immediately"
        ]
      },
      "problem_solving": {
        "score": 15,
        "matched_keywords": [
          "manage"
        ]
      },
      "decision": {
        "score": 15,
        "matched_keywords": [
          "manage"
        ]
      }
    },
    "aptitude_score": 69.74,
    "final_status": "strong"
  },
  {
    "candidate_id": "C002",
    "question_id": "Q2",
    "analysis": {
      "reasoning": {
        "score": 0,
        "matched_keywords": []
      },
      "scenario": {
        "score": 60,
        "matched_keywords": [
          "professional",
          "calm",
          "respectfully",
          "solution",
          "communicate"
        ]
      },
      "clarity": {
        "score": 90,
        "word_count": 19
      },
      "structure": {
        "score": 0,
        "structure_detected": []
      },
      "problem_solving": {
        "score": 0,
        "matched_keywords": []
      },
      "decision": {
        "score": 15,
        "matched_keywords": [
          "carefully"
        ]
      }
    },
    "aptitude_score": 70.95,
    "final_status": "strong"
  },
  {
    "candidate_id": "C003",
    "question_id": "Q3",
    "analysis": {
      "reasoning": {
        "score": 45,
        "matched_keywords": [
          "compare",
          "identify",
          "verify"
        ]
      },
      "scenario": {
        "score": 12,
        "matched_keywords": [
          "issue"
        ]
      },
      "clarity": {
        "score": 90,
        "word_count": 18
      },
      "structure": {
        "score": 12,
        "structure_detected": [
          "after"
        ]
      },
      "problem_solving": {
        "score": 45,
        "matched_keywords": [
          "correct",
          "identify",
          "verify"
        ]
      },
      "decision": {
        "score": 15,
        "matched_keywords": [
          "compare"
        ]
      }
    },
    "aptitude_score": 87.12,
    "final_status": "strong"
  },
  {
    "candidate_id": "C004",
    "question_id": "Q4",
    "analysis": {
      "reasoning": {
        "score": 15,
        "matched_keywords": [
          "prioritize"
        ]
      },
      "scenario": {
        "score": 0,
        "matched_keywords": []
      },
      "clarity": {
        "score": 90,
        "word_count": 15
      },
      "structure": {
        "score": 0,
        "structure_detected": []
      },
      "problem_solving": {
        "score": 15,
        "matched_keywords": [
          "efficient"
        ]
      },
      "decision": {
        "score": 15,
        "matched_keywords": [
          "prioritize"
        ]
      }
    },
    "aptitude_score": 56.1,
    "final_status": "average"
  },
  {
    "candidate_id": "C005",
    "question_id": "Q5",
    "analysis": {
      "reasoning": {
        "score": 15,
        "matched_keywords": [
          "understand"
        ]
      },
      "scenario": {
        "score": 36,
        "matched_keywords": [
          "professional",
          "issue",
          "communicate"
        ]
      },
      "clarity": {
        "score": 90,
        "word_count": 17
      },
      "structure": {
        "score": 0,
        "structure_detected": []
      },
      "problem_solving": {
        "score": 15,
        "matched_keywords": [
          "improve"
        ]
      },
      "decision": {
        "score": 0,
        "matched_keywords": []
      }
    },
    "aptitude_score": 66.99,
    "final_status": "strong"
  },
  {
    "candidate_id": "C006",
    "question_id": "Q6",
    "analysis": {
      "reasoning": {
        "score": 45,
        "matched_keywords": [
          "compare",
          "identify",
          "verify"
        ]
      },
      "scenario": {
        "score": 0,
        "matched_keywords": []
      },
      "clarity": {
        "score": 90,
        "word_count": 16
      },
      "structure": {
        "score": 0,
        "structure_detected": []
      },
      "problem_solving": {
        "score": 30,
        "matched_keywords": [
          "identify",
          "verify"
        ]
      },
      "decision": {
        "score": 30,
        "matched_keywords": [
          "carefully",
          "compare"
        ]
      }
    },
    "aptitude_score": 79.2,
    "final_status": "strong"
  },
  {
    "candidate_id": "C007",
    "question_id": "Q7",
    "analysis": {
      "reasoning": {
        "score": 30,
        "matched_keywords": [
          "because",
          "understand"
        ]
      },
      "scenario": {
        "score": 12,
        "matched_keywords": [
          "teamwork"
        ]
      },
      "clarity": {
        "score": 90,
        "word_count": 16
      },
      "structure": {
        "score": 12,
        "structure_detected": [
          "because"
        ]
      },
      "problem_solving": {
        "score": 45,
        "matched_keywords": [
          "improve",
          "reduce",
          "efficient"
        ]
      },
      "decision": {
        "score": 0,
        "matched_keywords": []
      }
    },
    "aptitude_score": 75.57,
    "final_status": "strong"
  },
  {
    "candidate_id": "C008",
    "question_id": "Q8",
    "analysis": {
      "reasoning": {
        "score": 15,
        "matched_keywords": [
          "understand"
        ]
      },
      "scenario": {
        "score": 36,
        "matched_keywords": [
          "professional",
          "calm",
          "resolve"
        ]
      },
      "clarity": {
        "score": 90,
        "word_count": 19
      },
      "structure": {
        "score": 0,
        "structure_detected": []
      },
      "problem_solving": {
        "score": 15,
        "matched_keywords": [
          "solve"
        ]
      },
      "decision": {
        "score": 15,
        "matched_keywords": [
          "carefully"
        ]
      }
    },
    "aptitude_score": 71.94,
    "final_status": "strong"
  },
  {
    "candidate_id": "C009",
    "question_id": "Q9",
    "analysis": {
      "reasoning": {
        "score": 15,
        "matched_keywords": [
          "verify"
        ]
      },
      "scenario": {
        "score": 0,
        "matched_keywords": []
      },
      "clarity": {
        "score": 90,
        "word_count": 19
      },
      "structure": {
        "score": 12,
        "structure_detected": [
          "first"
        ]
      },
      "problem_solving": {
        "score": 15,
        "matched_keywords": [
          "verify"
        ]
      },
      "decision": {
        "score": 0,
        "matched_keywords": []
      }
    },
    "aptitude_score": 53.79,
    "final_status": "average"
  },
  {
    "candidate_id": "C010",
    "question_id": "Q10",
    "analysis": {
      "reasoning": {
        "score": 30,
        "matched_keywords": [
          "analyze",
          "prioritize"
        ]
      },
      "scenario": {
        "score": 0,
        "matched_keywords": []
      },
      "clarity": {
        "score": 90,
        "word_count": 16
      },
      "structure": {
        "score": 0,
        "structure_detected": []
      },
      "problem_solving": {
        "score": 0,
        "matched_keywords": []
      },
      "decision": {
        "score": 45,
        "matched_keywords": [
          "decision",
          "prioritize",
          "carefully"
        ]
      }
    },
    "aptitude_score": 67.65,
    "final_status": "strong"
  },
  {
    "candidate_id": "C011",
    "question_id": "Q11",
    "analysis": {
      "reasoning": {
        "score": 15,
        "matched_keywords": [
          "understand"
        ]
      },
      "scenario": {
        "score": 36,
        "matched_keywords": [
          "professional",
          "respectfully",
          "solution"
        ]
      },
      "clarity": {
        "score": 90,
        "word_count": 18
      },
      "structure": {
        "score": 0,
        "structure_detected": []
      },
      "problem_solving": {
        "score": 15,
        "matched_keywords": [
          "manage"
        ]
      },
      "decision": {
        "score": 15,
        "matched_keywords": [
          "manage"
        ]
      }
    },
    "aptitude_score": 71.94,
    "final_status": "strong"
  },
  {
    "candidate_id": "C012",
    "question_id": "Q12",
    "analysis": {
      "reasoning": {
        "score": 45,
        "matched_keywords": [
          "compare",
          "identify",
          "verify"
        ]
      },
      "scenario": {
        "score": 0,
        "matched_keywords": []
      },
      "clarity": {
        "score": 90,
        "word_count": 17
      },
      "structure": {
        "score": 0,
        "structure_detected": []
      },
      "problem_solving": {
        "score": 45,
        "matched_keywords": [
          "correct",
          "identify",
          "verify"
        ]
      },
      "decision": {
        "score": 15,
        "matched_keywords": [
          "compare"
        ]
      }
    },
    "aptitude_score": 79.2,
    "final_status": "strong"
  },
  {
    "candidate_id": "C013",
    "question_id": "Q13",
    "analysis": {
      "reasoning": {
        "score": 0,
        "matched_keywords": []
      },
      "scenario": {
        "score": 0,
        "matched_keywords": []
      },
      "clarity": {
        "score": 80,
        "word_count": 14
      },
      "structure": {
        "score": 0,
        "structure_detected": []
      },
      "problem_solving": {
        "score": 0,
        "matched_keywords": []
      },
      "decision": {
        "score": 0,
        "matched_keywords": []
      }
    },
    "aptitude_score": 35.2,
    "final_status": "weak"
  },
  {
    "candidate_id": "C014",
    "question_id": "Q14",
    "analysis": {
      "reasoning": {
        "score": 15,
        "matched_keywords": [
          "explain"
        ]
      },
      "scenario": {
        "score": 36,
        "matched_keywords": [
          "professional",
          "customer",
          "solution"
        ]
      },
      "clarity": {
        "score": 90,
        "word_count": 17
      },
      "structure": {
        "score": 0,
        "structure_detected": []
      },
      "problem_solving": {
        "score": 0,
        "matched_keywords": []
      },
      "decision": {
        "score": 0,
        "matched_keywords": []
      }
    },
    "aptitude_score": 62.04,
    "final_status": "average"
  },
  {
    "candidate_id": "C015",
    "question_id": "Q15",
    "analysis": {
      "reasoning": {
        "score": 30,
        "matched_keywords": [
          "identify",
          "verify"
        ]
      },
      "scenario": {
        "score": 0,
        "matched_keywords": []
      },
      "clarity": {
        "score": 100,
        "word_count": 22
      },
      "structure": {
        "score": 0,
        "structure_detected": []
      },
      "problem_solving": {
        "score": 45,
        "matched_keywords": [
          "correct",
          "identify",
          "verify"
        ]
      },
      "decision": {
        "score": 0,
        "matched_keywords": []
      }
    },
    "aptitude_score": 72.05,
    "final_status": "strong"
  },
  {
    "candidate_id": "C016",
    "question_id": "Q16",
    "analysis": {
      "reasoning": {
        "score": 15,
        "matched_keywords": [
          "verify"
        ]
      },
      "scenario": {
        "score": 0,
        "matched_keywords": []
      },
      "clarity": {
        "score": 90,
        "word_count": 15
      },
      "structure": {
        "score": 0,
        "structure_detected": []
      },
      "problem_solving": {
        "score": 15,
        "matched_keywords": [
          "verify"
        ]
      },
      "decision": {
        "score": 15,
        "matched_keywords": [
          "carefully"
        ]
      }
    },
    "aptitude_score": 56.1,
    "final_status": "average"
  },
  {
    "candidate_id": "C017",
    "question_id": "Q17",
    "analysis": {
      "reasoning": {
        "score": 0,
        "matched_keywords": []
      },
      "scenario": {
        "score": 12,
        "matched_keywords": [
          "professional"
        ]
      },
      "clarity": {
        "score": 90,
        "word_count": 15
      },
      "structure": {
        "score": 0,
        "structure_detected": []
      },
      "problem_solving": {
        "score": 15,
        "matched_keywords": [
          "manage"
        ]
      },
      "decision": {
        "score": 15,
        "matched_keywords": [
          "manage"
        ]
      }
    },
    "aptitude_score": 54.78,
    "final_status": "average"
  },
  {
    "candidate_id": "C018",
    "question_id": "Q18",
    "analysis": {
      "reasoning": {
        "score": 30,
        "matched_keywords": [
          "identify",
          "verify"
        ]
      },
      "scenario": {
        "score": 12,
        "matched_keywords": [
          "issue"
        ]
      },
      "clarity": {
        "score": 90,
        "word_count": 18
      },
      "structure": {
        "score": 12,
        "structure_detected": [
          "immediately"
        ]
      },
      "problem_solving": {
        "score": 45,
        "matched_keywords": [
          "correct",
          "identify",
          "verify"
        ]
      },
      "decision": {
        "score": 15,
        "matched_keywords": [
          "carefully"
        ]
      }
    },
    "aptitude_score": 80.52,
    "final_status": "strong"
  },
  {
    "candidate_id": "C019",
    "question_id": "Q19",
    "analysis": {
      "reasoning": {
        "score": 30,
        "matched_keywords": [
          "because",
          "identify"
        ]
      },
      "scenario": {
        "score": 12,
        "matched_keywords": [
          "issue"
        ]
      },
      "clarity": {
        "score": 90,
        "word_count": 17
      },
      "structure": {
        "score": 12,
        "structure_detected": [
          "because"
        ]
      },
      "problem_solving": {
        "score": 45,
        "matched_keywords": [
          "improve",
          "reduce",
          "identify"
        ]
      },
      "decision": {
        "score": 0,
        "matched_keywords": []
      }
    },
    "aptitude_score": 75.57,
    "final_status": "strong"
  },
  {
    "candidate_id": "C020",
    "question_id": "Q20",
    "analysis": {
      "reasoning": {
        "score": 15,
        "matched_keywords": [
          "explain"
        ]
      },
      "scenario": {
        "score": 12,
        "matched_keywords": [
          "support"
        ]
      },
      "clarity": {
        "score": 100,
        "word_count": 20
      },
      "structure": {
        "score": 0,
        "structure_detected": []
      },
      "problem_solving": {
        "score": 15,
        "matched_keywords": [
          "support"
        ]
      },
      "decision": {
        "score": 0,
        "matched_keywords": []
      }
    },
    "aptitude_score": 60.83,
    "final_status": "average"
  },
  {
    "candidate_id": "C021",
    "question_id": "Q21",
    "analysis": {
      "reasoning": {
        "score": 45,
        "matched_keywords": [
          "analyze",
          "compare",
          "identify"
        ]
      },
      "scenario": {
        "score": 0,
        "matched_keywords": []
      },
      "clarity": {
        "score": 90,
        "word_count": 17
      },
      "structure": {
        "score": 0,
        "structure_detected": []
      },
      "problem_solving": {
        "score": 15,
        "matched_keywords": [
          "identify"
        ]
      },
      "decision": {
        "score": 30,
        "matched_keywords": [
          "carefully",
          "compare"
        ]
      }
    },
    "aptitude_score": 74.25,
    "final_status": "strong"
  },
  {
    "candidate_id": "C022",
    "question_id": "Q22",
    "analysis": {
      "reasoning": {
        "score": 0,
        "matched_keywords": []
      },
      "scenario": {
        "score": 12,
        "matched_keywords": [
          "professional"
        ]
      },
      "clarity": {
        "score": 80,
        "word_count": 14
      },
      "structure": {
        "score": 0,
        "structure_detected": []
      },
      "problem_solving": {
        "score": 0,
        "matched_keywords": []
      },
      "decision": {
        "score": 0,
        "matched_keywords": []
      }
    },
    "aptitude_score": 40.48,
    "final_status": "weak"
  },
  {
    "candidate_id": "C023",
    "question_id": "Q23",
    "analysis": {
      "reasoning": {
        "score": 0,
        "matched_keywords": []
      },
      "scenario": {
        "score": 0,
        "matched_keywords": []
      },
      "clarity": {
        "score": 90,
        "word_count": 16
      },
      "structure": {
        "score": 0,
        "structure_detected": []
      },
      "problem_solving": {
        "score": 15,
        "matched_keywords": [
          "manage"
        ]
      },
      "decision": {
        "score": 15,
        "matched_keywords": [
          "manage"
        ]
      }
    },
    "aptitude_score": 49.5,
    "final_status": "average"
  },
  {
    "candidate_id": "C024",
    "question_id": "Q24",
    "analysis": {
      "reasoning": {
        "score": 0,
        "matched_keywords": []
      },
      "scenario": {
        "score": 0,
        "matched_keywords": []
      },
      "clarity": {
        "score": 90,
        "word_count": 16
      },
      "structure": {
        "score": 0,
        "structure_detected": []
      },
      "problem_solving": {
        "score": 15,
        "matched_keywords": [
          "improve"
        ]
      },
      "decision": {
        "score": 0,
        "matched_keywords": []
      }
    },
    "aptitude_score": 44.55,
    "final_status": "weak"
  },
  {
    "candidate_id": "C025",
    "question_id": "Q25",
    "analysis": {
      "reasoning": {
        "score": 0,
        "matched_keywords": []
      },
      "scenario": {
        "score": 0,
        "matched_keywords": []
      },
      "clarity": {
        "score": 80,
        "word_count": 14
      },
      "structure": {
        "score": 0,
        "structure_detected": []
      },
      "problem_solving": {
        "score": 0,
        "matched_keywords": []
      },
      "decision": {
        "score": 0,
        "matched_keywords": []
      }
    },
    "aptitude_score": 35.2,
    "final_status": "weak"
  },
  {
    "candidate_id": "C026",
    "question_id": "Q26",
    "analysis": {
      "reasoning": {
        "score": 15,
        "matched_keywords": [
          "explain"
        ]
      },
      "scenario": {
        "score": 36,
        "matched_keywords": [
          "professional",
          "respectfully",
          "support"
        ]
      },
      "clarity": {
        "score": 90,
        "word_count": 16
      },
      "structure": {
        "score": 0,
        "structure_detected": []
      },
      "problem_solving": {
        "score": 30,
        "matched_keywords": [
          "improve",
          "support"
        ]
      },
      "decision": {
        "score": 0,
        "matched_keywords": []
      }
    },
    "aptitude_score": 71.94,
    "final_status": "strong"
  },
  {
    "candidate_id": "C027",
    "question_id": "Q27",
    "analysis": {
      "reasoning": {
        "score": 15,
        "matched_keywords": [
          "verify"
        ]
      },
      "scenario": {
        "score": 0,
        "matched_keywords": []
      },
      "clarity": {
        "score": 90,
        "word_count": 17
      },
      "structure": {
        "score": 12,
        "structure_detected": [
          "before"
        ]
      },
      "problem_solving": {
        "score": 15,
        "matched_keywords": [
          "verify"
        ]
      },
      "decision": {
        "score": 0,
        "matched_keywords": []
      }
    },
    "aptitude_score": 53.79,
    "final_status": "average"
  },
  {
    "candidate_id": "C028",
    "question_id": "Q28",
    "analysis": {
      "reasoning": {
        "score": 15,
        "matched_keywords": [
          "approach"
        ]
      },
      "scenario": {
        "score": 12,
        "matched_keywords": [
          "solution"
        ]
      },
      "clarity": {
        "score": 90,
        "word_count": 16
      },
      "structure": {
        "score": 0,
        "structure_detected": []
      },
      "problem_solving": {
        "score": 0,
        "matched_keywords": []
      },
      "decision": {
        "score": 45,
        "matched_keywords": [
          "decision",
          "select",
          "carefully"
        ]
      }
    },
    "aptitude_score": 66.33,
    "final_status": "strong"
  },
  {
    "candidate_id": "C029",
    "question_id": "Q29",
    "analysis": {
      "reasoning": {
        "score": 0,
        "matched_keywords": []
      },
      "scenario": {
        "score": 12,
        "matched_keywords": [
          "professional"
        ]
      },
      "clarity": {
        "score": 90,
        "word_count": 17
      },
      "structure": {
        "score": 0,
        "structure_detected": []
      },
      "problem_solving": {
        "score": 15,
        "matched_keywords": [
          "improve"
        ]
      },
      "decision": {
        "score": 15,
        "matched_keywords": [
          "carefully"
        ]
      }
    },
    "aptitude_score": 54.78,
    "final_status": "average"
  },
  {
    "candidate_id": "C030",
    "question_id": "Q30",
    "analysis": {
      "reasoning": {
        "score": 0,
        "matched_keywords": []
      },
      "scenario": {
        "score": 0,
        "matched_keywords": []
      },
      "clarity": {
        "score": 90,
        "word_count": 16
      },
      "structure": {
        "score": 0,
        "structure_detected": []
      },
      "problem_solving": {
        "score": 15,
        "matched_keywords": [
          "improve"
        ]
      },
      "decision": {
        "score": 0,
        "matched_keywords": []
      }
    },
    "aptitude_score": 44.55,
    "final_status": "weak"
  }
]